unitypackage_extractor/__init__.py
unitypackage_extractor/__main__.py
unitypackage_extractor/extractor.py
unitypackage_extractor-1.1.0.dist-info/LICENSE.txt
unitypackage_extractor-1.1.0.dist-info/METADATA
unitypackage_extractor-1.1.0.dist-info/WHEEL
unitypackage_extractor-1.1.0.dist-info/top_level.txt
unitypackage_extractor-1.1.0.dist-info/RECORD
