Metadata-Version: 2.1
Name: unitypackage-extractor
Version: 1.1.0
Summary: Extractor for .unitypackage files
Home-page: https://github.com/Cobertos/unitypackage_extractor/
Author: Cobertos
Author-email: me@cobertos.com
License: MIT
Keywords: untiy unity3d unitypackage extract tar extractor
Platform: UNKNOWN
Classifier: Development Status :: 5 - Production/Stable
Classifier: Intended Audience :: Developers
Classifier: License :: OSI Approved :: MIT License
Classifier: Programming Language :: Python :: 3.6
Classifier: Programming Language :: Python :: 3.7
Classifier: Programming Language :: Python :: 3.8
Classifier: Programming Language :: Python :: 3.9
Classifier: Topic :: Software Development :: Build Tools
Classifier: Topic :: System :: Filesystems
License-File: LICENSE.txt
Requires-Dist: tarsafe (>=0.0.2)
